janggu/__init__.py
janggu/__main__.py
janggu/cli.py
janggu/decorators.py
janggu/evaluation.py
janggu/janggutrim.py
janggu/layers.py
janggu/losses.py
janggu/model.py
janggu/utils.py
janggu/version.py
janggu/data/__init__.py
janggu/data/coverage.py
janggu/data/data.py
janggu/data/dna.py
janggu/data/genomic_indexer.py
janggu/data/genomicarray.py
janggu/data/nparr.py
janggu/data/visualization.py
janggu/resources/10regions.bed
janggu/resources/bed_test.bed
janggu/resources/positive.bed
janggu/resources/positive.bedgraph
janggu/resources/positive_gap.bed
janggu/resources/positive_shift.bed
janggu/resources/pseudo_genome.fa
janggu/resources/pseudo_snps.vcf
janggu/resources/region_w_strand.bed
janggu/resources/roi.bed
janggu/resources/roi_test.bed
janggu/resources/roi_train.bed
janggu/resources/sacCer3.chrom.sizes
janggu/resources/sample.bam
janggu/resources/sample.bam.bai
janggu/resources/sample.bed
janggu/resources/sample.bedgraph
janggu/resources/sample.bw
janggu/resources/sample.chrom.sizes
janggu/resources/sample.csv
janggu/resources/sample.fa
janggu/resources/sample.gtf
janggu/resources/sample.vcf
janggu/resources/sample2.bam
janggu/resources/sample2.bam.bai
janggu/resources/sample2.fa
janggu/resources/sample2_test.fa
janggu/resources/sample_equalsize.bed
janggu/resources/sample_fulltile.bed
janggu/resources/sample_fulltile2.bed
janggu/resources/sample_genome.fa
janggu/resources/sample_protein.fa
janggu/resources/sample_test.fa
janggu/resources/scored_region.bed
janggu/resources/scored_sample.bed
janggu/resources/scores.bed
janggu-0.10.2.dist-info/AUTHORS.rst
janggu-0.10.2.dist-info/LICENSE
janggu-0.10.2.dist-info/METADATA
janggu-0.10.2.dist-info/WHEEL
janggu-0.10.2.dist-info/entry_points.txt
janggu-0.10.2.dist-info/top_level.txt
janggu-0.10.2.dist-info/RECORD
