Metadata-Version: 2.1
Name: janggu
Version: 0.10.2
Summary: Utilities and datasets for deep learning in genomics
Home-page: https://github.com/BIMSBbioinfo/janggu
Author: Wolfgang Kopp
Author-email: wolfgang.kopp@mdc-berlin.de
License: GPL-3.0
Keywords: genomics,epigenomics,bioinformatics,deep learning,machine learning
Platform: UNKNOWN
Classifier: Development Status :: 5 - Production/Stable
Classifier: Intended Audience :: Developers
Classifier: License :: OSI Approved :: GNU General Public License v3 (GPLv3)
Classifier: Operating System :: Unix
Classifier: Operating System :: POSIX
Classifier: Programming Language :: Python
Classifier: Programming Language :: Python :: 3.5
Classifier: Programming Language :: Python :: 3.6
Classifier: Programming Language :: Python :: 3.7
Classifier: Topic :: Utilities
License-File: LICENSE
License-File: AUTHORS.rst
Requires-Dist: numpy
Requires-Dist: pandas
Requires-Dist: Biopython (==1.77)
Requires-Dist: h5py
Requires-Dist: pybedtools
Requires-Dist: pydot
Requires-Dist: pysam (!=0.15.3,<0.16)
Requires-Dist: pyBigWig
Requires-Dist: progress
Requires-Dist: matplotlib
Requires-Dist: seaborn
Requires-Dist: scikit-learn
Requires-Dist: scipy
Provides-Extra: tf
Requires-Dist: tensorflow (==1.14) ; extra == 'tf'
Requires-Dist: keras (<2.3) ; extra == 'tf'
Provides-Extra: tf2
Requires-Dist: tensorflow (==2.2) ; extra == 'tf2'
Requires-Dist: keras (==2.4.3) ; extra == 'tf2'
Provides-Extra: tf2_gpu
Requires-Dist: tensorflow-gpu (==2.2) ; extra == 'tf2_gpu'
Requires-Dist: keras (==2.4.3) ; extra == 'tf2_gpu'
Provides-Extra: tf_gpu
Requires-Dist: tensorflow-gpu (==1.14) ; extra == 'tf_gpu'
Requires-Dist: keras (<2.3) ; extra == 'tf_gpu'
